vfs_build/__init__.py
vfs_build/actors/Actor.py
vfs_build/actors/Analyzer.py
vfs_build/actors/Command.py
vfs_build/actors/Compiler.py
vfs_build/actors/Link.py
vfs_build/actors/LinkAndLaunch.py
vfs_build/cli/__init__.py
vfs_build/cli/cli_main.py
vfs_build/support/ActorSystem.py
vfs_build/support/Dependancies.py
vfs_build/support/Environment.py
vfs_build/support/File.py
vfs_build/support/Optionnal.py
vfs_build/support/Options.py
vfs_build/support/import_source_file.py
vfs_build/support/link_install.py
vfs_build-2024.1.10.0.dist-info/METADATA
vfs_build-2024.1.10.0.dist-info/WHEEL
vfs_build-2024.1.10.0.dist-info/entry_points.txt
vfs_build-2024.1.10.0.dist-info/top_level.txt
vfs_build-2024.1.10.0.dist-info/RECORD
